README.md
setup.py
data_kernelspec/kernel.json
data_kernelspec/logo-32x32.png
data_kernelspec/logo-64x64.png
trio_jupyter/__init__.py
trio_jupyter.egg-info/PKG-INFO
trio_jupyter.egg-info/SOURCES.txt
trio_jupyter.egg-info/dependency_links.txt
trio_jupyter.egg-info/requires.txt
trio_jupyter.egg-info/top_level.txt
trio_jupyter/resources/logo-32x32.png
trio_jupyter/resources/logo-64x64.png